hc_mul/__init__.py
hc_mul/hc_mul.py
hc_mul-0.2.0.dist-info/METADATA
hc_mul-0.2.0.dist-info/WHEEL
hc_mul-0.2.0.dist-info/top_level.txt
hc_mul-0.2.0.dist-info/RECORD
