Metadata-Version: 2.1
Name: hc_mul
Version: 0.2.0
Summary: Default template for PDM package
Author-email: NishNovae <raecrowned@gmail.com>
License: MIT
Project-URL: Homepage, https://github.com/NishNovae/hc_calculation
Project-URL: Issues, https://github.com/NishNovae/hc_calculation/issues
Requires-Python: >=3.9
